{
  "original": {
    "total_pixels": 1146880,
    "diff_percentage": 2.1645092933006533,
    "changed_pixels": 28537,
    "changed_percentage": 2.4882289341517856,
    "mean_diff": {
      "r": 5.5193097795758925,
      "g": 5.519876534598215,
      "b": 5.5193097795758925
    },
    "max_diff": {
      "r": 255,
      "g": 255,
      "b": 255
    }
  },
  "processed": {
    "total_pixels": 1146880,
    "changed_pixels": 22568,
    "changed_percentage": 1.9677734374999998,
    "diff_percentage": 1.8658128127553102,
    "processing_applied": {
      "threshold": 40,
      "morphology_kernel": 4,
      "blur_kernel": 0
    }
  },
  "note": "The \"processed\" statistics match the red highlighted areas in diff_highlight.png. \"original\" statistics are based on raw pixel differences without filtering."
}