{
  "original": {
    "total_pixels": 655360,
    "diff_percentage": 0.7362449496400123,
    "changed_pixels": 7063,
    "changed_percentage": 1.077728271484375,
    "mean_diff": {
      "r": 1.8771087646484375,
      "g": 1.8780563354492188,
      "b": 1.8771087646484375
    },
    "max_diff": {
      "r": 255,
      "g": 255,
      "b": 255
    }
  },
  "processed": {
    "total_pixels": 655360,
    "changed_pixels": 0,
    "changed_percentage": 0.0,
    "diff_percentage": 0.0,
    "processing_applied": {
      "threshold": 40,
      "morphology_kernel": 4,
      "blur_kernel": 0
    }
  },
  "note": "The \"processed\" statistics match the red highlighted areas in diff_highlight.png. \"original\" statistics are based on raw pixel differences without filtering."
}